ApolloClient.py
py_apollo_client-0.0.2.dist-info/LICENSE
py_apollo_client-0.0.2.dist-info/METADATA
py_apollo_client-0.0.2.dist-info/WHEEL
py_apollo_client-0.0.2.dist-info/top_level.txt
py_apollo_client-0.0.2.dist-info/RECORD
