Metadata-Version: 2.1
Name: py-apollo-client
Version: 0.0.2
Summary: python apollo client
Home-page: https://github.com/ztj1993/py-apollo-client
Author: ZhangTianJie
Author-email: ztj1993@gmail.com
License: MIT License
Keywords: apollo client
Platform: UNKNOWN
Requires-Dist: requests
